async43/__init__.py
async43/exceptions.py
async43/model.py
async43/servers.py
async43/whois.py
async43/net/__init__.py
async43/net/resolve.py
async43/parser/__init__.py
async43/parser/constants.py
async43/parser/dates.py
async43/parser/detector.py
async43/parser/engine.py
async43/parser/nameservers.py
async43/parser/structure.py
async43-0.1.2.dist-info/licenses/LICENSE.txt
tests/__init__.py
tests/test_ipv6.py
tests/test_main.py
tests/test_nicclient.py
tests/test_parser.py
tests/test_query.py
async43-0.1.2.dist-info/METADATA
async43-0.1.2.dist-info/WHEEL
async43-0.1.2.dist-info/top_level.txt
async43-0.1.2.dist-info/RECORD
