Metadata-Version: 2.4
Name: async43
Version: 0.1.2
Summary: Asynchronous WHOIS client for Python using asyncio. Supports IPv6 and IP rotation.
Home-page: https://github.com/devl00p/async43
Author: Nicolas Surribas
Author-email: nicolas.surribas@gmail.com
License: MIT
Keywords: whois,asyncio,async,ipv6,networking,parser,python,whois-client
Classifier: Development Status :: 4 - Beta
Classifier: Environment :: Web Environment
Classifier: Intended Audience :: Developers
Classifier: License :: OSI Approved :: MIT License
Classifier: Operating System :: OS Independent
Classifier: Programming Language :: Python :: 3
Classifier: Programming Language :: Python :: 3.10
Classifier: Programming Language :: Python :: 3.11
Classifier: Programming Language :: Python :: 3.12
Classifier: Programming Language :: Python :: 3.13
Classifier: Framework :: AsyncIO
Classifier: Topic :: Internet :: WWW/HTTP
Classifier: Topic :: Software Development :: Libraries :: Python Modules
License-File: LICENSE.txt
Requires-Dist: async-lru>=2.0.5
Requires-Dist: dnspython>=2.8.0
Requires-Dist: email-validator>=2.3.0
Requires-Dist: phonenumbers==9.0.22
Requires-Dist: pydantic>=2.12.5
Requires-Dist: python-dateutil>=2.9.0.post0
Requires-Dist: PySocks>=1.7.1
Requires-Dist: rapidfuzz>=3.14.3
Requires-Dist: text-scrubber>=0.5.0
Requires-Dist: tldextract>=5.3.1
Dynamic: author
Dynamic: author-email
Dynamic: classifier
Dynamic: description
Dynamic: description-content-type
Dynamic: home-page
Dynamic: keywords
Dynamic: license
Dynamic: license-file
Dynamic: requires-dist
Dynamic: summary
